index.py
search.py
mseep_crawl4ai_mcp_server-0.1.4.dist-info/licenses/LICENSE
mseep_crawl4ai_mcp_server-0.1.4.dist-info/METADATA
mseep_crawl4ai_mcp_server-0.1.4.dist-info/WHEEL
mseep_crawl4ai_mcp_server-0.1.4.dist-info/top_level.txt
mseep_crawl4ai_mcp_server-0.1.4.dist-info/RECORD
