Metadata-Version: 2.4
Name: mseep-crawl4ai_mcp_server
Version: 0.1.4
Summary: MCP Server for Crawl4AI
Author-email: mseep <support@skydeck.ai>
Requires-Python: >=3.9
License-File: LICENSE
Requires-Dist: mcp>=1.2.0
Requires-Dist: crawl4ai>=0.1.0
Dynamic: license-file
